spakky/plugins/typer/__init__.py
spakky/plugins/typer/main.py
spakky/plugins/typer/post_processor.py
spakky/plugins/typer/py.typed
spakky/plugins/typer/stereotypes/__init__.py
spakky/plugins/typer/stereotypes/cli_controller.py
spakky/plugins/typer/utils/__init__.py
spakky/plugins/typer/utils/asyncio.py
spakky/plugins/typer/utils/casing.py
spakky_typer-5.0.1.dist-info/WHEEL
spakky_typer-5.0.1.dist-info/entry_points.txt
spakky_typer-5.0.1.dist-info/METADATA
spakky_typer-5.0.1.dist-info/RECORD
