Metadata-Version: 2.3
Name: spakky-typer
Version: 5.0.1
Summary: Typer CLI plugin for Spakky framework
Author: Spakky
Author-email: Spakky <sejong418@icloud.com>
License: MIT
Requires-Dist: spakky>=5.0.1
Requires-Dist: typer>=0.20.0
Requires-Python: >=3.11
